.coveragerc
.gitignore
.scrutinizer.yml
.travis.yml
LICENSE.txt
MANIFEST.in
README.rst
setup.cfg
setup.py
doc/Makefile
doc/conf.py
doc/index.rst
doc/make.bat
whatami/__init__.py
whatami/misc.py
whatami/parsers.py
whatami/plugins.py
whatami/registry.py
whatami/what.py
whatami/whatutils.py
whatami.egg-info/PKG-INFO
whatami.egg-info/SOURCES.txt
whatami.egg-info/dependency_links.txt
whatami.egg-info/requires.txt
whatami.egg-info/top_level.txt
whatami/minijoblib/__init__.py
whatami/minijoblib/_compat.py
whatami/minijoblib/hashing.py
whatami/tests/__init__.py
whatami/tests/fixtures.py
whatami/tests/test_misc.py
whatami/tests/test_parsers.py
whatami/tests/test_plugins.py
whatami/tests/test_registry.py
whatami/tests/test_roundtrips.py
whatami/tests/test_what.py
whatami/tests/test_whatable.py
whatami/tests/test_whatutils.py
whatami/wrappers/__init__.py
whatami/wrappers/what_sklearn.py
whatami/wrappers/tests/__init__.py
whatami/wrappers/tests/test_what_sklearn.py