Metadata-Version: 2.1
Name: whatami
Version: 5.1.15
Summary: Easily provide python objects with self-identification
Home-page: https://github.com/sdvillal/whatami
Author: Santi Villalba
Author-email: sdvillal@gmail.com
License: BSD 3 clause
Platform: Any
Classifier: Intended Audience :: Science/Research
Classifier: Intended Audience :: Developers
Classifier: Topic :: Software Development
Classifier: Topic :: Scientific/Engineering
Classifier: License :: OSI Approved
Classifier: Programming Language :: Python :: 2
Classifier: Programming Language :: Python :: 2.7
Classifier: Programming Language :: Python :: 3
Classifier: Programming Language :: Python :: 3.5
Classifier: Programming Language :: Python :: 3.6
Provides-Extra: docs
Provides-Extra: pandas
Provides-Extra: numpy
Provides-Extra: sklearn
